{"name": "Kavalipati Sai", "email": "kavalipatikiriti@gmail.com", "mobile_number": "8639006122", "skills": ["Engineering", "Pandas", "Python", "Cloud", "Numpy", "Ms excel", "Aws", "Programming", "Html", "Analytical", "Analyze", "Css", "Email", "Excel", "Responses", "Healthcare", "Computer science", "Matplotlib", "Algorithms", "Technical", "Sql", "Ui", "Ai"], "college_name": null, "degree": null, "designation": null, "experience": null, "company_names": null, "no_of_pages": 2, "total_experience": 0, "Matching Percentage": "59.6182"}